bluefog
