Metadata-Version: 2.1
Name: bluefog
Version: 0.2.0
Summary: A distributed training framework for diffusion or consensus-type algorithm.
Home-page: https://github.com/ybc1991/bluefog
Author: Bicheng Ying
Author-email: bichengying@gmail.com
License: UNKNOWN
Platform: UNKNOWN
Classifier: License :: OSI Approved :: Apache Software License
Classifier: Programming Language :: Python :: 3
Classifier: Programming Language :: Python :: Implementation :: CPython
Requires-Python: >=3.7.0
